test/__init__.py
test/file.py
test/test_file.py
tintin/__init__.py
tintin/__main__.py
tintin/api.py
tintin/auth.py
tintin/config.txt
tintin/env.py
tintin/logging.py
tintin/online_serving.py
tintin/util.py
tintin/file/file_manager.py
tintin/file/http.py
tintin/file/minio.py
tintin_sdk-0.2.0.dist-info/METADATA
tintin_sdk-0.2.0.dist-info/WHEEL
tintin_sdk-0.2.0.dist-info/entry_points.txt
tintin_sdk-0.2.0.dist-info/top_level.txt
tintin_sdk-0.2.0.dist-info/RECORD
