Metadata-Version: 2.1
Name: tintin-sdk
Version: 0.2.0
Summary: A Python SDK for Tintin
Home-page: https://github.com/footprint-ai/tintin-sdk
Author: hsinho yeh
Author-email: hsinho.yeh@footprint-ai.com
License: MIT
Platform: UNKNOWN
Classifier: License :: OSI Approved :: MIT License
Classifier: Programming Language :: Python :: 3
Classifier: Programming Language :: Python :: 3.6
Requires-Python: >=3.6
Requires-Dist: requests
Requires-Dist: dill
Requires-Dist: minio
